amber_electric/__init__.py
amber_electric/exceptions.py
amber_electric/main.py
amber_electric/skeleton.py
amber_electric/auth/__init__.py
amber_electric/auth/auth.py
amber_electric/geocode/__init__.py
amber_electric/geocode/geocode.py
amber_electric/market/__init__.py
amber_electric/market/market.py
amber_electric/price/__init__.py
amber_electric/price/price.py
amber_electric/protocol/__init__.py
amber_electric/protocol/protocol.py
amber_electric/usage/__init__.py
amber_electric/usage/usage.py
amber_electric-0.0.17.dist-info/AUTHORS.rst
amber_electric-0.0.17.dist-info/LICENSE.txt
amber_electric-0.0.17.dist-info/METADATA
amber_electric-0.0.17.dist-info/WHEEL
amber_electric-0.0.17.dist-info/top_level.txt
amber_electric-0.0.17.dist-info/RECORD
