Metadata-Version: 2.1
Name: amber-electric
Version: 0.0.17
Summary: Unofficial Amber Electric API Library
Home-page: https://github.com/troykelly/python-amber-electric
Author: Troy Kelly
Author-email: troy@troykelly.com
License: cc0
Project-URL: Documentation, https://github.com/troykelly/python-amber-electric/wiki
Project-URL: Issues, https://github.com/troykelly/python-amber-electric/issues
Platform: any
Classifier: Development Status :: 4 - Beta
Classifier: Programming Language :: Python
Requires-Dist: backoff
Requires-Dist: requests
Provides-Extra: testing
Requires-Dist: pytest ; extra == 'testing'
Requires-Dist: pytest-cov ; extra == 'testing'
